{"paths":{"0":["tex_zombie/zombieSkill_icon_18",2],"1":["audio_game/footsteps",1],"2":["audio_game/shot_sd",1],"3":["audio_game/hurt_range",1],"4":["tex_zombie/zombieSkill_icon_33_2",2],"5":["audio_game/shot_gj",1],"6":["tex_zombie/zombieSkill_icon_22",2],"7":["audio_zombie/LuoLei",1],"8":["audio_game/flag",1],"9":["audio_game/shot_cjj",1],"10":["audio_game/shot_gtst",1],"11":["tex_zombie/zombieSkill_icon_13",2],"12":["audio_zombie/LevelUp",1],"13":["audio_game/bag",1],"14":["tex_zombie/zombieSkill_icon_14",2],"15":["tex_zombie/zombieSkill_icon_11",2],"16":["tex_common/icon",2],"17":["tex_zombie/zombieSkill_icon_21",2],"18":["audio_zombie/jingyan",1],"19":["tex_chain_logo/theta_logo",2],"20":["tex_chain_logo/core_logo",2],"21":["tex_chain_logo/ethereum_logo",2],"22":["tex_chain_logo/polygon_logo",2],"23":["tex_zombie/zombieSkill_icon_12",2],"24":["audio_game/shot_dao",1],"25":["tex_chain_logo/somnia_logo",2],"26":["tex_zombie/zombieSkill_icon_34_1",2],"27":["tex_zombie/zombieSkill_icon_8",2],"28":["tex_zombie/zombieSkill_icon_32_2",2],"29":["audio_common/coin",1],"30":["tex_zombie/zombieSkill_icon_0",2],"31":["audio_game/shot_sq",1],"32":["audio_zombie/zombie_win",1],"33":["tex_chain_logo/bnb_logo",2],"34":["tex_zombie/zombieSkill_icon_7",2],"35":["audio_zombie/QuanPingBaoZha",1],"36":["audio_common/ui_caidai",1],"37":["tex_zombie/zombieSkill_icon_34_3",2],"38":["audio_zombie/chilunStart",1],"39":["tex_chain_logo/base_logo",2],"40":["tex_zombie/zombieSkill_icon_24",2],"41":["audio_common/turntable",1],"42":["audio_game/shot_jtl",1],"43":["tex_chain_logo/avalanche_logo",2],"44":["tex_zombie/zombieSkill_icon_33_3",2],"45":["audio_game/shot_tb",1],"46":["tex_zombie/zombieSkill_icon_3",2],"47":["audio_game/shot_rsq",1],"48":["audio_game/changeWeapon",1],"49":["audio_game/shot_mq",1],"50":["tex_zombie/zombieSkill_icon_15",2],"51":["tex_skin/player_3",2],"52":["tex_zombie/zombieSkill_icon_2",2],"53":["tex_zombie/zombieSkill_icon_27",2],"54":["tex_zombie/zombieSkill_icon_9",2],"55":["audio_game/death",1],"56":["audio_game/shot_ju",1],"57":["audio_common/bgm_ui",1],"58":["audio_game/hurt_melee",1],"59":["tex_skin/player_2",2],"60":["tex_zombie/zombieSkill_icon_4",2],"61":["audio_game/hurt",1],"62":["tex_zombie/zombieSkill_icon_5",2],"63":["audio_common/ui_upgrade",1],"64":["tex_zombie/zombieSkill_icon_19",2],"65":["audio_zombie/chilun",1],"66":["audio_common/diamond",1],"67":["audio_game/shot_nnp",1],"68":["tex_zombie/zombieSkill_icon_10",2],"69":["audio_game/shot_mb",1],"70":["audio_zombie/GameOver",1],"71":["audio_zombie/zombie_fail",1],"72":["tex_zombie/zombieSkill_icon_16",2],"73":["tex_zombie/zombieSkill_icon_26",2],"74":["tex_zombie/zombieSkill_icon_32_3",2],"75":["tex_zombie/zombieSkill_icon_20",2],"76":["tex_chain_logo/optimism_logo",2],"77":["audio_zombie/ShieldDestroy",1],"78":["tex_zombie/zombieSkill_icon_33_1",2],"79":["tex_zombie/zombieSkill_icon_29",2],"80":["tex_zombie/zombieSkill_icon_23",2],"81":["tex_zombie/zombieSkill_icon_1",2],"82":["tex_chain_logo/scroll_logo",2],"83":["tex_zombie/zombieSkill_icon_31",2],"84":["audio_common/bgm_6",1],"85":["tex_chain_logo/MetaMask_logo",2],"86":["tex_zombie/zombieSkill_icon_6",2],"87":["audio_zombie/ranshao",1],"88":["audio_game/shot_cfq",1],"89":["audio_common/btn",1],"90":["audio_game/shot_jgb",1],"91":["audio_game/shot_hdl",1],"92":["tex_skin/player_1",2],"93":["audio_game/shot_ak",1],"94":["audio_game/shot_szg",1],"95":["audio_zombie/bingdong",1],"96":["audio_zombie/Ranshaopingposui",1],"97":["tex_zombie/zombieSkill_icon_17",2],"98":["audio_zombie/ZombieLaugh",1],"99":["audio_game/explo",1],"100":["tex_zombie/zombieSkill_icon_32_1",2],"101":["audio_game/shot_ld",1],"102":["audio_game/reload",1],"103":["tex_zombie/zombieSkill_icon_34_2",2],"107":["tex_chain_logo/optimism_logo",3,1],"109":["UI/UIRankingsPanel",0],"110":["tex_zombie/zombieSkill_icon_2",3,1],"114":["prefab_zombie/boss11",0],"115":["UI/RankingListItem",0],"120":["prefab_zombie/boss2",0],"121":["tex_skin/player_1",3,1],"122":["UI/UIADPanel",0],"123":["tex_skin/player_0",3,1],"124":["UI/UIOverPage",0],"129":["prefab_weapon/weapon_sd",0],"132":["tex_zombie/zombieSkill_icon_26",3,1],"134":["prefab_weapon/weapon_ak",0],"136":["prefab_zombie/zombie_bomb",0],"137":["prefab_weapon/weapon_cjj",0],"140":["prefab_zombie_skill/boss_border",0],"143":["prefab_zombie_skill/jingyan",0],"144":["prefab_zombie/zombie_drum",0],"145":["UI/UITurntablePanel",0],"148":["prefab_weapon/weapon_hdl",0],"150":["tex_common/icon",4],"151":["tex_zombie/zombieSkill_icon_0",3,1],"152":["prefab_zombie/boss9",0],"156":["prefab_zombie/zombie_basic",0],"157":["tex_zombie/zombieSkill_icon_15",3,1],"158":["tex_zombie/zombieSkill_icon_19",3,1],"161":["UI/UIUpgradePanel",0],"162":["prefab_weapon/weapon_jtl",0],"163":["tex_zombie/zombieSkill_icon_9",3,1],"168":["tex_zombie/zombieSkill_icon_10",3,1],"172":["prefab_weapon/weapon_mq",0],"174":["prefab_zombie/zombie_run",0],"177":["tex_zombie/zombieSkill_icon_11",3,1],"179":["UI/UIGamePage",0],"180":["prefab_zombie_skill/zombieSkill_hudun",0],"181":["UI/UIPausePanel",0],"182":["tex_skin/player_2",3,1],"187":["prefab_zombie_skill/zombieSkill_fire",0],"188":["UI/FlyIcon",0],"189":["prefab_weapon/weapon_jgb",0],"191":["prefab_weapon/weapon_ju",0],"192":["tex_chain_logo/avalanche_logo",3,1],"195":["prefab_zombie/boss10",0],"200":["prefab_weapon/weapon_szg",0],"201":["tex_zombie/zombieSkill_icon_5",3,1],"206":["tex_zombie/zombieSkill_icon_1",3,1],"208":["tex_zombie/zombieSkill_icon_24",3,1],"211":["prefab_zombie/boss5",0],"212":["UI/WeaponListItem",0],"214":["prefab_zombie/boss3",0],"215":["prefab_zombie_skill/effect_qpbz",0],"216":["UI/SkinListItem",0],"217":["tex_zombie/zombieSkill_icon_34_3",3,1],"219":["tex_zombie/zombieSkill_icon_4",3,1],"222":["tex_zombie/zombieSkill_icon_20",3,1],"224":["tex_zombie/zombieSkill_icon_3",3,1],"225":["tex_zombie/zombieSkill_icon_23",3,1],"227":["UI/UIRevivePanel",0],"228":["tex_skin/player_3",3,1],"233":["UI/UIGameLoadingPage",0],"235":["tex_zombie/zombieSkill_icon_6",3,1],"236":["tex_zombie/zombieSkill_icon_31",3,1],"240":["tex_zombie/zombieSkill_icon_8",3,1],"241":["tex_zombie/zombieSkill_icon_34_1",3,1],"242":["tex_zombie/zombieSkill_icon_33_2",3,1],"243":["prefab_weapon/weapon_dao",0],"244":["prefab_zombie/boss1",0],"247":["prefab_zombie_skill/zombieSkill_sjgx",0],"248":["tex_chain_logo/ethereum_logo",3,1],"250":["UI/UIHomePage",0],"251":["tex_zombie/zombieSkill_icon_13",3,1],"252":["prefab_weapon/weapon_mb",0],"254":["tex_chain_logo/bnb_logo",3,1],"257":["prefab_zombie_skill/effect_death",0],"261":["tex_zombie/zombieSkill_icon_7",3,1],"262":["prefab_weapon/weapon_gj",0],"263":["tex_zombie/zombieSkill_icon_14",3,1],"266":["tex_chain_logo/polygon_logo",3,1],"267":["prefab_weapon/weapon_cfq",0],"268":["prefab_zombie/boss13",0],"270":["prefab_zombie_skill/zombieSkill_24",0],"271":["tex_zombie/zombieSkill_icon_22",3,1],"272":["tex_zombie/zombieSkill_icon_34_2",3,1],"274":["prefab_zombie/boss6",0],"278":["prefab_weapon/weapon_gtst",0],"283":["prefab_zombie_skill/zombieSkill_26",0],"285":["tex_zombie/zombieSkill_icon_32_1",3,1],"287":["tex_chain_logo/theta_logo",3,1],"288":["tex_zombie/zombieSkill_icon_32_2",3,1],"290":["tex_zombie/zombieSkill_icon_32_3",3,1],"291":["tex_chain_logo/base_logo",3,1],"292":["tex_zombie/zombieSkill_icon_21",3,1],"294":["prefab_zombie/zombie_poison",0],"295":["prefab_weapon/weapon_ld",0],"296":["tex_zombie/zombieSkill_icon_16",3,1],"297":["prefab_zombie/boss12",0],"298":["tex_chain_logo/core_logo",3,1],"304":["UI/TipsPanel",0],"306":["prefab_zombie_skill/zombieSkill_bishou",0],"309":["tex_zombie/zombieSkill_icon_12",3,1],"310":["prefab_zombie/zombie_tank",0],"311":["prefab_zombie_skill/zombieSkill_shandian",0],"312":["tex_zombie/zombieSkill_icon_33_1",3,1],"313":["prefab_zombie_skill/zombieSkill_3",0],"314":["tex_chain_logo/somnia_logo",3,1],"315":["prefab_zombie/boss8",0],"316":["prefab_weapon/weapon_tj",0],"318":["tex_zombie/zombieSkill_icon_33_3",3,1],"319":["prefab_weapon/weapon_nnp",0],"320":["prefab_zombie/zombie_jump",0],"325":["prefab_zombie/boss7",0],"326":["prefab_weapon/weapon_tb",0],"328":["tex_zombie/zombieSkill_icon_29",3,1],"330":["tex_skin/player_0",2],"331":["tex_zombie/zombieSkill_icon_27",3,1],"335":["prefab_zombie/boss4",0],"336":["prefab_weapon/weapon_fs",0],"337":["prefab_weapon/weapon_rsq",0],"338":["prefab_weapon/weapon_sq",0],"339":["tex_zombie/zombieSkill_icon_18",3,1],"340":["tex_chain_logo/scroll_logo",3,1],"341":["tex_zombie/zombieSkill_icon_17",3,1],"344":["prefab_weapon/weapon_sq2",0],"346":["tex_chain_logo/MetaMask_logo",3,1],"348":["prefab_zombie_skill/zombieSkill_feilun",0]},"types":["cc.Prefab","cc.AudioClip","cc.Texture2D","cc.SpriteFrame","cc.SpriteAtlas"],"uuids":["003GabM1FBXaNd6GkhJNT1","045Z+0vtBPjI1BT8gYfKgC","054yi3nEtPEqwrKKyuHO5z","06G0S3Qy5AToVKsQPhsPi/","06n1oQ7UtONpQZb5T19k0A","08LftwDW5HHqI5e298OBiP","09Gm3PGGBOKaSoHvD+ll5j","09R+asw9pM15doaQq/yx4F","0bFN28DIhPR7WbWAJIiCFk","0dVwM2ZphJjJEhHy8BV6lG","10e1YjNoFLvJASvxaADmAk","17BhCJXfJJwpCw+bCrlDEB","18/JoMardAWKx7xXTuGT1r","1aUtfrND5Cy7KZANBwtlUi","1fH9Oy1PFDy5k1dDRTw0T2","25PJPTUypFBrtlqH8Na18y","26FSxtvVlFoJFF1XAmtnaw","2duA2xDMNHK4vPWn3rCK2b","2d3U2EH+lD/Y5M/cCv3wnb","31XcKl5CVAsYpj/G2z9bIE","34t5dCWMhMEoyQObvIVr+n","39BlU97XpM/r18NLB713il","3aI0ZtaIdFMaEUkaAHJXLZ","3bxZtCm89HDI0GAvgqWsw9","3eevE+ZG9OCZYaK5JLpIuD","41iD0j2tdDM5KmtxgYF+7I","44aQfMpGVN+5jtCzh+awVi","46LwWIGbhPTqSSWKiBbk4D","4ereLhdUdIuK7fFf5iu2ey","4e0NzfCmJBn7le9RUe/EGH","5127tf2mxILoB0YEXyswfk","5ap9r+y3NGzIedYpt0VLHz","5b2YZu+4FJ8IUefzde8p4h","5flq1/9B5JRr7xAShh7uJs","60XfE6A9BONYjp2dv3cvx9","61BRCWFb9GK50w48B6SGue","671dODbS9OgbCTF/wHziV5","68RF/9R2tBpZxycfe18AJJ","6aNWqCmoZGdJOG/LStcFPx","7226CvlaVAu7QXZkQfYQxr","775C+uZ1xFZpjmQqeLliMh","7br8TyQHdGr6dd73E+JNJF","7cXFYdb5BNy4wUO9RG1omA","7fUIQcU55Cdqxz/qwARYLL","81SRrQCzBP2rMninDtdapg","86H2JVH25LUYANfaKFDczs","86grEx0YFPf46fHDA7UThL","8ap/nNvplFvJc4dvE8o9gs","8f6Jqn9RxKfZazDRxW9WCn","96J2reLFpNApet2U7cnraZ","97NBrLsc5Jl40ZiluJmppG","9aAYbazGJDlaFDVauDB6KY","9cYscZs/VLRYwnd+J6PF1y","9fIsIFFzJHTpsFAR6cPWty","9fKn3sJENCprN0tt54mS8p","a0U4lnOf1LPLVQH5/rx+F/","a0h9uGwKZIRbgJb2Ai21eH","a4/wQnCvdGu6c5uXG2K7cr","a5V9q+J4pE3J/I07k0x1bJ","a8u0rxoClM96h2HGq33jKY","aapCodzQRLuI+SdNnf1OB5","accXvXYjxN44dmXICJJQgb","afq5j6RtdNN6d9K7yl3pA4","b3BrV4BRxMYIID7ezgJiWq","b4D2C6/j1AV6FIUrPt9Isv","b5TbQV+fBKZY2FFujCL7KQ","b8oOFmhedGzqeNx/DVJGG9","bb/Mdbnq1EBY/GOuhVX9Zb","bb/xxaPjxMiJb9EOa70oCA","bc5O4HqiNHELV1FqPuMlJq","c4Ep7gcNxBKqWQfgQk+YzL","c4IPBCZDlOWaAZFfbH3kAi","c7QLnX+l9B/Yt/oQlBVoLo","c70tdQ/rpBTaKEhz1iCHSW","c8FmavF2pE5qDPW1K7Jba0","cbYv8nx3JMMI5OvW7cxToK","ceKmLc6iFBR55MWOltI7Ps","cfijdk79ZHpId8oj2UGrSf","d5eIixRDRCkK/TFsVtAMQN","d6En3Y8JRJU7ofMWFCdn1+","d8DO5qI99GcbjkzqwNabXI","d8Sp5WuL9ELpLh4RZ5mOaY","d9n/GkZVBFWrGo0hB0LWEv","ddnHy6TJRBqIjsc2aUSgoh","deqVR53r5OeKCaIX814LmJ","dfh9tfdABPe51rpypiBUfM","e0fRa9lghEIYaOI7s+G6rj","e4JdyE0U9CULW9w7AV7QGp","e5XzUwY6VNw6MRvijrtgqg","e8thjkUExLTb9jMxZSIshj","e85xAjZUZJHqKGGwa3wzeJ","e89hpUn1VGTK81/02DWdTM","eeY7FHh2FOHYvM0SOvIJdM","eevfDuxa9NipN6qmOfhZoi","efFznSpp5DBIxJTuHlYZea","efgHaPLN9KvbW6G6beWYOH","f0UPZMHWJJyqslE9lNRkZK","f3gdFGARFDdo58ljHYv+TP","f5XHOUumxJFLwDT1bB2Mwp","f7jU1cgzxLWZC7ghps5ilE","f7tYmyU6RBHb/Vq4YBvxFw","f9qziK6DRLjoZRoVO5x1sE","ffaywGGxZNzI+UE6vj/FDA","ffmiH11hJH2YroNHIajcuP","00AuTKsC9K77ieC9Lv2kPd","01Duuv62dMeoQ7M0yWnAMN","01FazWJhJA1oOUngKpAFeK","04NS/BeC9KVIKJYFI9BTp3","06GoXEMnBN85AifZzjMVHC","06vC5fKPxF+6p9Ndih39NJ","08Sa7jK0lFq6dIYANtUTFS","08gD8EBflKcoR3m7qcwMqX","0bM+7M/gxABpfdvjvxY8RO","0bwtGI2C5C+bba0nSSO/e8","0dSn8mSQxLEJadqqLgW+Mw","0dW5itf/9OjYT0qmnz5sIx","0eQ9NbzgVCQoYW9+VhkZje","0f2rLGHmtEaZ3emMMeWbja","11Q2PZqndKQLZkutlUk/US","12B2fj83lOt5o2o3wRpiS2","12tIo+2QhKgb6vCVZW2H4S","138EpxT4hDd49IfU0tPfrU","14EnLLXX1B4aeAyXMSKjVc","14Lu4qaglGKp/rUoo3QEXt","14xRVY899FyaXkw5imPoKX","17yfaGvltEUbQJ+DnrQ4gI","19i32MlLtD86nPjwSypVl/","1aJFyRvEpHj6giebzVPeqb","1cmKCBGDFCNIq5Nyjn/pXy","1eHmICiOFE8pTX7EcCchGr","1e0c/KNclAgb9XC/YyRvG4","1e9FKXosJJsqLudKQKAIJA","1fIx7bWuZIVLNcNMNP6r4g","1fmX747CtA65wiJhirJJel","1fqqYypbpFL4EiuyF542rO","20rn8yHyxKc6aHsoZC6mtX","21F6r9vvRNUJtkhKllK41m","26XT6A/JBKKLLmhhvUMiEy","27ygcmqE5LQ4IrMoF6ReLg","28focSG/5BB63yAa4a2hLb","29+uFpTBBFJJVY6Hc2TPQB","2bA6n6h1xGVrhefQ8En55I","2c3beiOxFPA7bmEDRZQTPc","2et/T2L41D/KhT5zs+57m3","2fcqnmAfZNsoR8bBLJ1sKT","2fd653JYdDNIYo+l9gPjld","2fej/9HplPypcPvVauu/zx","31WQWDoEBD37Qzd3/i/+oI","33XhlwXVFFlLAlyaQ0xBp/","34v+hhVMlF1YG9+V4nkLCe","35Pby9tkJEs7XEBB8HNKIl","35eH7h7sdLAo0w0ufJXTWk","38P3qPAwxHGpC1pgLJZwk2","38hrAWuuhMHbPvTOZoS2TL","39Vug2KBNJaKH+y2wgtE5S","3bs1OA6HpNaotDplf1N32b","3cDgTJdaVCfItlz9su1v7I","3cGNioZURAqIbkn0tn4IwX","3eVUHnnWhG/4L182UfFlLr","41AUZfgKhAH6bS8R65WUY2","44h3CSg39EaoyYsbSk1DEy","44iANdkN1KzYKGCxlqy3BW","45ljtWaxROZp9wREXt9Tg1","456UM/l45CFqgrBPLH7TOs","46xxpP+6VKgbXkLhxv5tOa","48GeKx7+xOf4GxTvXJ0Wz4","48L6vz5wJB1LKc9UAC6LLk","48pBJdKpFNQ6gmKaKSyQuw","4b+TEZurdNPpkEED2bZZ7a","4fGVpZhQhMLZ4oKw7/6O4J","4fMBhZfJ5KjaxQBHeVaKwk","4fPVUcHhVD+4oB3HWzv8jn","4fbsZQrrJF9LZkegDZ7Rpv","524VPTeRlIt7f0E3VVwPZe","52+TcBPlRNnrmrOgFM+eND","55pI3HoC1O1pzS1E2gAzmF","56fc2Ai/RFNYpaMT8crweK","56ys8EQOpLrIhGymmrSCWk","562bXZfAdLForSeSy59+RU","57KMx2/NlMFbjyZD9xzp3f","58CcfHdTRFppM6OnxcBUSf","58ZW6GustFqoYZKmRz6C8G","58zxdtdkRLUarc7IaLdFCq","59nD7gb+lO/rnr8T2XT9+D","5aZEJ52ylCPpKqpzK5Urkp","5dX5ARZyxLJ5h3nvdU/115","5da09T+vJHi4uvBJqsQOQX","5eaLiksgtB8Imje1/8cSkQ","5fBm/FsVBHmJT4D0F8qgQ2","5fswxaj09Pa4otcfchlCKW","5f2dVz4SNGD7mp5Jq2NifP","5f6rN0E51O25KA0w6AvUR4","62aiGUFKVOXry0uHEXbGWQ","62eWOUs8FCboGJlBTPtiyN","63WV0MEW9KRJaxcOfWsVRg","65P9bPrbxDs67/SvTbG/3m","6aK32GaT1LnqpvejUkNzNd","6ainHPgKtKJ6UblRTxAQHA","6cGANzXT5Ala1xwVCo8i5S","6cOFW2DYVMqZMgrtbXS1eQ","6cONNsWfZBHIZ3uNWTSfHC","6cd/tSvEFB372r1INvYiGr","6dKdzWimhC6KMm741RISVK","6eBWFz0oVHPLIGQKf/9Thu","71VhFCTINJM6/Ky3oX9nBT","72Z0RZ+xZHFpm1cZMzli3e","72nIhqFiNPSIiJYNM1iZPu","73vFT69MND/qLtRgXKo5Qz","734BG/MVxGRq4gqo3DAmD8","74McTYIrNOfJb6JnkaxnNM","76MK57cWFEc55NxV7qHLD5","76OvUuNEFPPb1/29y+dq8M","77yg6H8cZFCbn3R6t7FmNG","770okFti5Iupv4osIEPujr","772zwTw8RNY5WfjgogsNM1","774H90NohBTaJMoo/HfhJz","78lXeL9C1JCYwXiMp+cIR5","79SJSrortHLqWLVgFPXID1","7913qAtLFNBb5xe5/m50JY","7a3D0J2Z1Hc7+4VESUCvBP","7cEFFSM3VDjpUPcYhqT0eM","7cVduscVdCn7F5NR98P/Nb","7c6cUg0D9PtqFO/HlBtJ6j","7eRlNSmO5MmYkPNcT5ZAgv","7elz+94VtORLidVsNXvBW1","7etutGG0VP1pjeUFtnwW/g","7eu7g45UJJdJHMVLgxdVBc","7flXiYN2ZIZJgn3sMOxjKT","7fxXBpgthFOZ7Pjy52qmku","80D5x9VCpKOJcLPfGG47/x","80PcEK/65P5KxdYFeNVhQN","81tikFHPhM5qJR9KednbXz","83t4aqfAVGD6UjXyACey/S","85ZX1AhmlCcI5Xk20lRcpM","87x9l71KlDYrEi5de9PhxD","88HiEfKKVIsbCBatDdbOWg","88fpSngxVGEJCtUuNLi3X6","89JP+grKJAmrPK1XHvSV70","8aK0WaI0hIabKFaEfW+Wpz","8bR+wHAhBMRZwfwlQqJtkY","8b29mGTVVOdK9Iy0Ec3oor","8cRbMcn+FMwK85TwlAn3Xn","8dcu2U0ClNkr7uRk6l2uQT","8dzyQ+1JxPxKLvFQnemA8j","8emQLEpLhDf6MqBv1wOYm3","905TNowVxHl51+clMfL+yp","91sz0eoelIOKvgp/+kynd+","95iUPAcHVL4ayH5nArNONR","95voR80F5KHqX9c4TNwiTH","96s306jp5NO7AwZTgMK24D","96tEA8ZtBHMqtkpwq4Q7sE","972AuRoNFJGqux2/q81f/h","98VNLbbzJHV4tnCnJH9sVE","99G4OBdJdIfrRW+8Kezxr4","99KSJX6mpEYIBgo+JE6oKv","99SX1KDapDSq88GvEDZhxX","999yA7i+5A475NkB1I4d6T","9dvx3LAUdCLZFbZ+3r94L4","9eeMx4HoxIwIV/mFoSNcSq","a0LUKTuxREOrrhYngDKPv/","a043A/COhM7bdjU3nhSth+","a2u2Vk0ARLUY+5XeVi49bn","a4PXSidL5NCqR7/nEO9gf9","a4VouLbE1C9rTLhep4izq3","a6upX688JLCKd72qNA6nYo","a8Unv+O91DF7DHKFEqbQBJ","a88IbvEfVEwYVzWkPyZ1jE","abMtKUvohFx58ujOvhrQ+4","abZqDdr9VOmLO6eWhe3pxD","achXLiFa5HNK1ubkfOAUrI","adY40j3YZKBLMT9rMSaCnA","ad0qwEpe9FQ4xwfSj/GTSD","b0uPiMY8pJbqZy0Z7MbG1Y","b0uwf7gJ9KSokTRcaMlFyE","b016zNmEVFt48VE9ytI7mg","b27uDg6uZJNr0YT1CesM3C","b4P/PCArtIdIH38t6mlw8Y","b5ZkQ4xypJ6bJABrykUkV9","b8nGm4H05MbLRcVistLDdo","baMMClr/1G4a8VysdeuZcH","baVm9hZ8FJpKrBkEmGNuUD","bcXEnXqtRGRb24TrMsOamw","bdoLXlS1dFxa0+EUXWt3s3","be6Zd3k5JDAbYOBNMBqfyq","bfjjMPlm1PEaBRhmjvB95R","c0kCwscC9I0ozNljx6MLao","c0yvEbjiBFG5vO0Et6D8N2","c1i4Ed8p5O2rq4LwWsD1Rt","c2Be23DIJJK4ohneWAa2nX","c3RpLZ5Y5O14r3WvU6+cN3","c4Sa6AFg9JHa1FCgQL6KPI","c4YU8bDURMgZVgqejH/E+d","c6jsYzUtJIHbw95K2+NKd3","cbxBJydj5NlL/CeTpHEvTe","ceDeUgcntKEaU06pTkIx1O","ceHBEGMOpFtqv1atjQPPTT","ce3QJIpxVEc5Xhaa0opufR","cf7fd33kNPlIBBYk9q47O2","d1WPIGbrtIG5eY/z9deT1P","d5o9UThlBFKY90EVRbZhY7","d6ygUJE9pKtblnKquII0yv","d7MQmDY2NLQ4m+kSx2pBZa","d7Nz6abKBENonXKvtQIudF","d7RCFuQFhNNaCPm9wCUMm1","d7+KHb8wFMgrxkOewST7qU","d8HsitJHxOYqo801xBk8ev","d9aziAeypNqKQRh5SjRd5n","d918ZTUNRAoo51xXnDhgYt","dabQbI5j1Bm4oqHWtzIk6b","daqoD5UtJE7ZqiJ0icbnTE","daqomkigxBz7m+tQs4Vy5E","db/mEdQupBXbuqfH6RMLso","dc9Kha/2ZCcpxoqwnCVXvM","dc+BDbxNtAAImO0UJ+v3h4","ddGnC8EhJJUYZFsqCbpfzt","ddOd95Q4FFoI92L3iAxIRA","ddvSsOQ0VK5bCCqqU9PTS/","e1S2ikuwBInIOn0FWYDK52","e2mrypePtPh4/G555c0CGP","e3lM4Uno5FvKV47ITrFVHY","e7LhvJERNLi7/bOqVQE2k9","e7Lp1OHeVKyLPkJO5ZYOrj","e8TCj8BDpEpaH/KzKv/57u","e8Ueib+qJEhL6mXAHdnwbi","eaTfHcyQtPC7D2Lyqy0Cy7","eaUiBl+WtCvaJH84fLvwtN","eboLeEDUhB0YmQeHFcBD85","ecmv4qzRdKhqVLfgB2V0B0","eczc20AKJPQYF0C9E9B16Q","edCnonGKZBpqa+D8rVtgTD","edaikXua1D2Zqs2Z13Ih4A","f0e6yXaatHSJCm/VojLIrf","f1EC+ulQ5ImZ8IxIiO3GNU","f1W8eKCPxM8IolRgMAE1pT","f1e0J9/YRCTI402m1FvzS0","f13GVwc0RHGYIqLmo/dDg3","f3gjrW+PZLRqv6dUnie64v","f4ed9SVD1IEZk17HTmsWmq","f5hLL6obdNDKdz8IqJrpaI","f8FSnJB8RJAYHw2WHtBnS3","f8X3qVTYlKDp2KodTiMEl8","f8wdsvMe1O/6VHVLMaOPlR","faHWgSs2BARYkuJsHTge9u","faNquHMBBPdYg4GI+JlZ2Q","fbPgOivNJCjLHEbwl3R29G","fbWbGpM9JEvbMZ2xQwOfif","fbXAzareVLLK1mYPNgXJGz","fcqPS7y+dDsKHTmL5rAV1H","ffQOOrE+xEw5h2rCtBlbne","00clQ8hphHdpJAwWsUeV7y","01y7p1M+dFFr/MhXkL/++X","019qeNnY5GR6Yyp7SnoRFN","03HRVS5HhM35x8QRqqMomK","034jVTGXdOGLNzgJLQ3Vwh","038fQ4ju5BKpm6D8OdeqBQ","03/kQAvfxJHI7U551+wsto","04DwGv0B1OGY8pYPsYrtbz","05Ld1dBZFO67se081oCNt0","06dXZn0WRK1acfaSwhuLQn","06jCioB6tJC6fQJhvxR5tw","06q2V9FUJCyb9484pP7Whg","07fNHNx7VNf65MOclZ8T8z","07ze+kcYJLxKZ0b/Kb2pGJ","08iO6Uz1dNhJY04qgEVzJc","08jERFaQVGoLA4MkrVVeUI","08moofIiNPvrnBGd6hmN21","08tCfPxl9PVqMCl0qXcBlG","0847Ym1thFHJNd7KysePCK","0ar6g6caJIhJRW1ldIqTDQ","0a7tvpWCxDAoHrjrF3D9a2","0bdi88VKVIn7ajhYiUc9MQ","0beA8pMBJArIhDso5wjODC","0bgERnVb9O7qHtnw3+1Vgh","0cXaHWnvhE8bu/MwAeqh6R","0czg4NyZROCKjgWlHg3+ib","0dJF7xX79Puoz1BVtt5ItR","0e814cMshLv6JHsBYFltjq","0feCOU1TlM5YLsKTmhnG7I","0fuaUz2wlOhLZqMwfhNvo7","1032IV7yBJG4/lwuAhskjO","106OAgt4NMxph6DYRHSUr/","10+Lo3TKlJvJ9siLRjbXsH","11YFq69KVIS4sPHjS3vBx+","12artUzIdJzY1CadBPxTbK","17f/ZFupFPPrWtqNO8GQqX","1aTfP6GG5Pi6lQrTkIsJl6","1dXIKd0h5E2axyE1HpEQhb","1dpmwyQalNOImfA0TlnEZg","1ec/G8seNJ7460aPlo4J1H","1feZRdp3RAtIGmgOY2OMCZ","20PWDOl7NAH5TOxOyGvCsH","200zLsMLtCOKlqSPlReVKO","21pP82Ak1C2LB0uw7pNQ6m","21vuAgQapISJ7j8h3IumnS","23oHEOcWNAy62YTYSqT76P","24xHEACiBHXLy82mn8QzLn","258kAoQbJL5K7PZU+1/het","26XMTXU19OIor5WXpNJOHR","29FYIk+N1GYaeWH/q1NxQO","2abmv0UJNMlrHtaiBTqlsl","2adJPbc0pOrokaRKFoTwJo","2bgK0fmH1Dsq3eVHi01N44","2bwgYPyMFEr6fQ1pFfwZb1","2dOddN83JNLK/zNelKHGqK","2dx2bumK1K2pMRDHDGMrIx","2emz6ZFjlADJtUUHkly0k5","2fEFgKlJdE35QpQ39dYPff","2flaAv+UtGH5dfHFxJCrd1","303AIVG65CgJzTyg6ONX6f","32Z2YkOfBEf6/vymYf7eCV","33IP/52exNoqD3LdmC9Ztn","33OvEmdSxMVZDeWXQAB3mk","33Sa6GDANCZIi36wW3+s5S","35kBA2KyRKGahxW/jdujpg","389/StKtBNKoo+U/hfuH2V","39BcxudPpCd4RR0gl8Lhp3","39NDDDkpRNUbhxE+Fnw/kY","39WScT/atNKKW13S+wfatA","39n3yxIDVOzqSb+U3nYT9/","3aZGeiY/RKE7QMiYJeciPJ","3ae7efMv1CLq2ilvUY/tQi","3bIwEZtApESrEXO4wo++Vy","3bYteGcYNI7aj1K2P13wZQ","3fQKB/PvtIsKULPkQRlERJ","40upEIXmhL1qi4IjTV47vF","42HpuoiZVLnZcVnEXZQWO3","42/6q+pzBJvYv1EUPmLR+d","43eZFZ4nFEDKxYJQ6qL9YJ","44YtANVkFJBIFyMVQIwiGT","442TizGo9AkaDeHmEVaYZS","45T/mlekZLJblO00ZPUma2","46WgzuJBhFPqVKFpRbg5c1","46b/JlVxdCVYtqXQNTgy+e","46c2At1wJAjKWTKJ7ni6zx","469u4aOPtCcbjNiWKAT2GL","47vMJjQOpMcbgLXsOM5o0x","4aQ1WqkFJFnazMJhVpMuj4","4eCQgZU01DrLY3LtzE1KoY","4ejbfxLYRGPIttm/RgHI38","4feVSU+VJLkohWvf1/GdU9","51JwD7aEJB0rsS1XI6xYLt","51gqQ4q65FyJ9qYdz4uP/9","52AnLwqH1IyJNO6bEi4Cvx","52RJe2aRRLfZpqSbIqettc","53oj4M+IJBPK6OL1P1Saj7","53+wISCNFOk7c4Gt4+iFus","54KHXWh+pOt65kRBl/uOXE","54Uz8M1uVBYpphuspT5g4s","54xGcVqPZNFLpcbsNXA1Pr","56D/5cwfVOUaFuR8Af7npD","57H+nDEuhLhrZvQX+iaKHe","57oTsWbHFHaI6vzQJMZw17","5bbYE5+0ZPL4EtTtNF61JA","5dCYTbHnVKlJFrZ+AjZJPG","5dQGjeaPNKK6vkDdY2kTS6","5eSOj1wclPYYczxwDnYmyh","5evNI+Le5MNpQ4+JM1918O","60NqRkyQpMuZMccQHVektg","608qI1kH9PaqCWgWk2v2A0","64djc2w6hFBZSVWdElC996","6770vAC05DCr7Du++VWoM9","68OJJPNtdCg6AUeSqnWYbx","68WzRIlRBNb5CTEZW49sd8","69SM4PuiZEB6Pw9X/CSgmI","6aIEEHb8tFJZJclcVH+TjS","6aUhFCDylCZrTngOjnXOFE","6bewGxE7xPKpUxG7Q0+7Lq","6bfKakanxE9ZWzvhFCeC68","6cZSMrZVRJD4JFaq8VWN6h","6dhNRftjZJqLhcLtXrY/6C","6d1K3Yf9dDUqsDLdyh0d1n","6d91qAgpRO7rTnUdo+XTgZ","6eqlLqfgVOT5b1xj1hhzpO","6fgBCSDDdPMInvyNlggls2","71oIQR/w1BZKkUgz6xeIv2","72BeL3hAdM0ZTghqLzuZyh","72ZqykuaNDQ7U4AQLAXrDl","73NZlUC39Hfr4je4UCdMtG","73hh4ivzhI4rvDrQSW4Sql","74LHpXkCZBcZViGjyKmh3i","74ktdlyJZC84TgcgPk4wZq","74sm/yc7RFxpB3vQ4mRkdp","74+Q7pI/hCUaCQ+xPcZSdd","76SC5VdXhMzJW/ELLOpbLa","76+uYPDGlIGLhjOo/tLh/A","77i/g9jOFJwpsT3InVNtqp","780hXeMIpMrbPml/0m8G3U","78970ETExD3rdkrKSqKERR","7aCFlg9FZMZ58pAay+wiEx","7aNX0FAVxKWIeWuXt8AlKe","7a/QZLET9IDreTiBfRn2PD","7bioLL93VI+b6kVdpILF4b","7cYd9nPZhJnIC3QJuVpHgD","7d1JQ01PxF+IzX87FT8ka9","7edJR/nsZLkIvO6ls9K+fr","7euJ6wZWBJhqC/w/hY+Y2s","7f6JqkDjtAioh9dQedQ+Dt","81MI5fT39Hq7HrIZpFA75Z","82ATwJb0tLeaV9kGwFw99i","83nIOMMI5DMrdWBWzJWuOJ","84BJJ9MOZOyonJHEjnh3gV","84isExmsBBBZzGHmzh30KL","84mwkQvYpA5YMFRAFa6Ske","85FKJpkBhI4L2pbLuWwT1g","86JY4OZjVAXqQdc6+fR9st","86Z3mERBdBE76xyfIC0u+w","86jVT+MOlNtIU1glc/N2uh","87CyzU/CdHk75/QvW3pbcE","87IFW431JKd5DyY6UttDWe","87gP3Lv3NLBq6gmC7Z2MPd","8byp1kwNtKpKeo4hhSSOxo","8byuU6s5dM3Jcf+wmkhUCC","8c20Sso/ZEn7NUfNSM+EBh","8di1rNqwpMSroys8NB5DV1","8el3k1SKFME4O/Q12Tq98V","8fuJ2/BVtNIY1rCFpb8HSw","90QAkmFWRIKqFDKzLtQ+qX","90Q4S/6GBCAbR9mDULTMWR","91j6koUjJBmpoGruE0Ytn6","91ksMKaHRM9K9esB0KnfqA","93Tfl0X9JCfYH43wh3vXbx","94fneHF+xDNLJYU7ALZisv","94mF0s9WxBKLNAKvTpZnHF","94mfvDWD5CWLReS1R6INmz","941Q7etPRDca7oWBBFolwA","97ZElx/eVM3LljppRV/Nf8","973fyChBNNO7W/qNgy+UjR","98ojnMgd9Agp58eowgF3ZX","98542xGVFPo55oL29LtEav","99okpClqFARITMLfrGu7yF","99/2ocuUBP4Joe1CqNad9r","9aX0U6a65ChIUgxbRprJ1l","9ah4ZtZkNEu4SrO5kyLENx","9bvaMerUlDyary99mJa6xp","9dq2X39JdPmIuGM7CJfZpj","9d2eqSgFpMb68tVnWo+0Qy","9eQHLjNMRHD7r/YhGJ86Ny","9ecU8gCuZFrY9CERxL0XXq","9euL2sHyVKIa1dwLwN0umm","9e9FzRZ7RN3LwJBC84ngh8","a0yZYqyG5GX6rq8F4Ud1o6","a00brXdTFDT57BgvkjZDqF","a10CTZRNpHEb3yHmxeDg4V","a1+CgdUTlD+r3/XVNDt9wF","a2MjXRFdtLlYQ5ouAFv/+R","a4EPiFZlZMqIHBj3M2eXcF","a5EZXTlb5Do4h6BSHHCUuS","a56C3OCjJPM5m8HqMm+CMw","a8A+/ssZxHHb1PRt9RMz9I","a8X1no2X9OJoJYWJaKWrh7","a8f2RZJwpCiJWDNoDoSW0V","a8iwaDxbhCx7N2TZZCt+5B","a9KyrAIVxM96Vo4PUYPQWW","a9RG96BfpNLrSGEQFYQLv2","aawWcOu8hD6bt568zDtb/O","aboA6kg+pPuKt9AGzPJCcm","abv5vmv85Kbb6PVo4Attlf","ab2JsnfbNDAYP3mOpZ8ef/","acus9envFKV4r9wg+eLbiP","acwa7uydlFjaAVWhwmSp45","acxXmNYd9PqIlKwI336OP6","adk0XRcm1JVKQ2CnSRdFMd","adpA6hB/1F5IBUk4l6Mw0E","afUVN4owtBZrBm5cBpA/m3","af1OqO9eJHw5gIEe+ig+en","b0SOCoos1JW4AlNRgTaKze","b0YzMwcIVMEbcGsUjbY0ap","b1E2BGKCdALJxFGAZjsVUV","b1VALcQxZELowP3SqkxjwI","b2WXrG1gRH3rxr9JJu+lcY","b2aHrECZ5APKGS/0d2hvT1","b3SAtWUClMf4a7Qca70mhZ","b4KpMUCMpPsJ8vgMdeYgJU","b5jgGPAOhGn5vQ1uEQT+mb","b6oN4sFlxG96UvHugFN2ST","b6ukCl0llGyJLJF6ssOwt8","b68MmaxHhFZ517qVqfSWNs","b7qH/NijFNWZWTsp7DX7fS","b7tSWNGMdGbJycX+ugFkNk","b77/WjtBBEar8wIIGZItdq","b8/cp1vLlIHZDJWlC5OWy8","bbCMkqQkVJj7GojDwW3R+d","beExbdm6pFJqWABP619hDe","c0QJQlU1pC8bNPvDcZhQ7F","c01OYDSTpBzKL/HlsOCDWH","c3gRu/gqRC0ZgS9eY/pfVu","c3w/9WkOROBaxPnjvqR9k0","c4gw2BTSpH3IiCgYqvBNpN","c7FApy3PVFDoLgFUs6e2kG","c77P2xJbNB2KP04Id47wiF","c8CLzWdRRBr613Lmf1N31Q","c8rCx8/eJLyYhkCI+8RkkV","cbpvBBZv5FD551ZDuajoyH","cczdaLlYtCCJUo8p5h4GZK","cdXz/YZWNPqLyBhkikpO6f","d0TBroFd1LV7NNITQ0FaLZ","d1th+7csJPHqgKI+NGjjMH","d2sJ3XlrhHjrnLGjplGq2q","d2zMGFnpJAtJQOOunKgEar","d4JvrNcd1Jqow2pJy5Bo/I","d4hNfA4ChGUoYqyADPkZcl","d4uc1eA6FBOIbWo7j5dD5p","d5tCKfJzBJYrbSYP45i0XG","d7HmljVU1AVKcTtCyGi2bm","d8CJfCGLFHjIDwIukOHSK/","d8Tiz6uu5F5qbbJFxFW4MI","daRl2bGqdAM6OIsQDd+Ldb","dbNUTYyeJCm7sBBSaqwR9R","dbbhPi8y1DXoyK2G85++3P","dbrPrjwcBDqLNJfHbIxOo0","db3ehXdQtEl40+U4Ufxhbn","dcXRJeCvdH8I36+sbrmvBS","ddBXr7e4xEmaJLp9++9Zbs","devms6oQJDGp0jK15Cxrfn","e1WNbH0m1MB4Wn/S0dcsgP","e1pToqxf9EfqC69Jlk0JFN","e3CTc3E/pBnbYyINGpKoFS","e3ReZtsuNCbZ4kTF6YPC6h","e3Zu58qrFPx45dDtDpxaZO","e4AfImxQFBFLm94YOJsghC","e4jeUWTZ1LE5oF0hJ939oo","e4+CkhEjJLloeMdEBPTM/R","e6HwOR0opJ3ajYTLj0Jwlf","e6X3mW6PFB4Jhi1KETPgt8","e7Z3wQxFtI4YUutfQjpAxp","e7q6FL+VZEgLJUjVeDLic/","e8qGVY4yNLNogC4/Q8YWma","e97GVMl6JHh5Ml5qEDdSGa","eafSrbgRpCe67KBK/PvbUT","eauA/+KgBIjrIX4TazDdyn","ebQgEM3g9MYYThmqxEYLo5","ecpdLyjvZBwrvm+cedCcQy","ecqQ0Eg6hMjKI9RKpVwkMM","ec4GHiz1xCCIOaRE3TTZ0k","efueeD0ulEFrbDKSD7RDFB","f0BIwQ8D5Ml7nTNQbh1YlS","f1wFUuSE1I0oyoBO88P3cY","f1wkR+M0hNj6Pnp1nNv/Jh","f179ymRtxGI4Y7/q7D53xM","f27SCMnd1N3aj45ruHkbeG","f4LihUm9ZME7c3XeV35mLF","f8VJyzi49OtJFFnpjzRZ65","f87SuOcPBKTZY6UEwtY5EF","f9QQWw6GpAWozzLHqUL2yO","f9VuYy9+hETb0IqyNEwz6q","f9f5WcYOZCs5kfJFBWme3a","f91wjc6v1CTb9allePGNWu","faJ+WakTVD/IDzC2131zWe","faNDrIZxJP4oKYUHewoAJL","fbfDiUV9hJragsdKa3nDkR","fbteUR1oFI7IRAg/CWtkOP","fcflG2vnBMo7TWb8kWbAVQ","fdX7Zz8hRCXbdMqxwT9wuA","fd5rm5BYtDYZLYNWxNGri/","ffCcXGg2BPm6BIfcRddHxo"],"scenes":{},"redirect":[123,0,397,0,420,1,436,2,473,1,490,1,531,2,536,2,544,0,547,0,567,2,570,0,623,2,631,1,330,0],"deps":["main","internal","resources"],"packs":{"014340ba5":[355,379,400,494,294,598],"01624c80a":[129,429,438,461,524,552,642],"01b2d691b":[550,615],"01bbb427d":[390,270],"01cc66a9e":[357,215],"01ffbe236":[138,147],"02135f097":[121,216],"024168754":[143,577],"027cb37b3":[412,148,413],"028d0e80c":[603,306],"02f1c8530":[183,322],"030cd5b37":[104,0,106,108,4,111,6,112,113,116,118,119,11,125,126,127,128,130,131,14,133,135,15,16,141,142,17,146,19,20,149,153,21,154,22,155,23,159,25,26,160,27,164,165,167,28,169,171,30,173,175,176,178,184,185,186,33,190,34,193,194,37,196,197,198,202,203,204,205,39,207,209,210,213,40,218,220,221,223,226,43,230,44,231,232,46,238,239,245,246,50,253,255,256,51,52,258,53,54,260,264,265,59,60,269,62,273,275,64,276,277,279,280,68,281,284,286,289,72,73,74,75,293,76,78,299,79,300,301,302,303,80,305,81,82,307,308,83,85,86,317,321,323,324,327,329,92,332,333,334,97,100,342,343,345,103],"03162ac7c":[361,366,399,404,418,423,428,432,443,179,458,465,483,487,492,501,507,514,525,528,546,556,560,580,584,592,596,600,605,619,628,639,644,645,651],"031f5dde8":[375,405,187,565],"0387bfdf4":[172,441,527],"03f0c7279":[374,214],"03ff03072":[424,278,594],"0464b4f88":[200,517,576],"04a30f3ee":[257,578],"04bb93a41":[140,403],"0515d0841":[359,195,249],"05a0721e1":[416,572],"05a7f8407":[381,174],"05cc12cf7":[442,464],"05f509b6d":[181,601,634],"06232225a":[274,586],"06923f761":[120,470],"06a073eff":[188,478,516],"06d7d5ec5":[427,313],"06fec73d6":[114,395],"070d8d8d0":[434,243],"073608889":[521,593,348],"07a10869e":[337,648],"07b191a66":[548,608],"07bce3ee0":[354,383,402,422,161,469,499,512,522,545,562,574,646,647],"084d59311":[385,282,310],"089a42b77":[144,526],"08a3c1716":[373,320],"08af16e7f":[368,376,386,388,394,408,150,431,447,453,457,460,467,468,491,503,513,551,558,559,564,571,579,606,632,637,638,640,649,653],"08e14c28c":[482,247],"0937a4f30":[156,569],"09a93f76c":[180,549],"09f44eb65":[358,336],"0b0046842":[325,636],"0b44814a9":[371,415,476,519,554,585],"0b9f24efb":[364,401,475],"0bc17e335":[510,244],"0c339d10f":[398,627,635],"0ca1109a7":[377,145,440,459,484,509,541,575,641],"0cf3a5c97":[448,538],"0d1e4f7dd":[229,347],"0d4204583":[152,477],"0d9a11916":[349,353,367,380,384,387,393,406,417,419,426,430,433,446,454,455,463,466,479,485,488,496,497,502,506,515,250,529,530,537,542,543,557,561,590,597,602,610,612,613,614,617,620,622,624,626,654],"0dae45faf":[511,283],"0ddf6f2cd":[582,315],"0de356ea7":[389,391,407,410,439,449,452,480,227,568,621],"0ea92eb22":[444,297],"0ed919d8e":[378,409,450,268,609,652],"0ef5cbae4":[356,540,555],"0f475540d":[362,451,523,566,583,319,630],"0f57f803b":[351,136,495,505,595,643],"0f7d54e60":[396,563,591,295,607],"0f8e58ee7":[363,625],"0f9037f3e":[489,535,262],"0f9b36ada":[372,382,124,421,445,472,493,498,504,553,581,587],"0fa1756a3":[360,392,137,539,616],"0ffe62cb0":[350,311]},"name":"bundleRes","importBase":"import","nativeBase":"native","debug":false,"isZip":false,"encrypted":false,"versions":{"import":[105,"f7282","014340ba5","f53eb","01624c80a","eb021","01b2d691b","8c6c2","01bbb427d","de80d","01cc66a9e","4a181","01ffbe236","a8347","02135f097","4f55f","024168754","4ec05","027cb37b3","ecf3b","028d0e80c","12301","02f1c8530","f01d6","030cd5b37","7ab60","03162ac7c","de49e",352,"0f8b9","031f5dde8","a5303","0387bfdf4","11de2","03f0c7279","e9e19","03ff03072","0a33d",107,"abbf6","0464b4f88","a8b74","04a30f3ee","85a99","04bb93a41","0eb39",1,"526d1","0515d0841","4c9f9","05a0721e1","07d4e","05a7f8407","e4e0a","05cc12cf7","a5b78",2,"4d80a","05f509b6d","f4136",3,"c5a39","06232225a","c4e74","06923f761","17d2a","06a073eff","d5d32",109,"fe5cb","06d7d5ec5","da20f","06fec73d6","7b82d","070d8d8d0","d547c","073608889","4e0ee","07a10869e","1b761","07b191a66","10b22","07bce3ee0","32f34",5,"225ed",110,"d5a68","084d59311","bc1a9","089a42b77","c3d5d",365,"84514","08a3c1716","74189","08af16e7f","89bcd","08e14c28c","0b8d0","0937a4f30","c1004",7,"63414","09a93f76c","ea047","09f44eb65","4ac5f",369,"2ae56","0b0046842","68dd0",8,"b12b4","0b44814a9","5e2da",370,"de495","0b9f24efb","ea0b6","0bc17e335","e9b69","0c339d10f","a9ccb","0ca1109a7","78d1c","0cf3a5c97","5f0a1","0d1e4f7dd","93f30","0d4204583","9a705",9,"3946c",115,"1c7c6","0d9a11916","1b90f","0dae45faf","811b1","0ddf6f2cd","01883","0de356ea7","547a7","0ea92eb22","faff1","0ed919d8e","aa6c2","0ef5cbae4","f210b","0f475540d","81508","0f57f803b","36e50","0f7d54e60","056ab","0f8e58ee7","bee06","0f9037f3e","d546a","0f9b36ada","fd87c","0fa1756a3","52134",117,"47036","0ffe62cb0","c1173",10,"51a6a",122,"bacb1",12,"99f6f",13,"ee3cf",132,"5c9b3",134,"5340d",139,"915be",18,"44f39",411,"ccdeb",151,"f6336",414,"347d3",157,"019db",158,"fdd90",24,"542c6",425,"b5312",162,"87100",163,"5bf8e",435,"8549a",166,"08eac",168,"afcfa",437,"8e6ee",29,"bb2d6",170,"687c8",177,"735e2",182,"d9833",31,"00c65",32,"5e083",456,"b5f39",189,"04d2b",191,"211ca",35,"5ddf9",192,"4a0bf",36,"d3b1c",462,"bf74b",38,"94620",199,"a81b3",201,"b7d30",471,"63f4d",474,"7b482",206,"51255",208,"cdc93",481,"a8dab",211,"4464e",212,"9c354",486,"bdb40",217,"ea418",219,"8e190",41,"0212a",42,"9c02f",222,"442f6",224,"850bd",225,"649d7",228,"bf028",500,"3a520",233,"8468c",45,"81b0a",508,"f9121",234,"24e53",235,"a1233",236,"e6920",237,"e7d77",47,"1285b",240,"1c960",241,"627c4",242,"90cb8",48,"b4af8",518,"5b74b",520,"b0527",248,"93b26",49,"a0d49",251,"ef448",252,"db9d9",254,"10db1",532,"3340d",533,"95264",534,"8646f",259,"3593a",55,"1c55f",56,"c7c02",261,"8f4bb",263,"cb304",57,"1b2e2",58,"24d9f",266,"8ce7f",267,"256ee",61,"c41c8",271,"9d9ed",272,"fa74a",63,"1a85b",65,"4e029",573,"9b21d",66,"b121f",67,"cb35f",69,"f8d3b",285,"d1c54",287,"8caa0",288,"72f66",70,"d866f",71,"dae87",290,"933ec",291,"d9271",292,"484f1",588,"44baa",589,"3aa46",296,"6d303",77,"c446a",298,"d6e3a",599,"acef4",304,"ebf49",604,"782d5",309,"fec93",611,"28f06",312,"c3f3e",314,"e54a7",316,"9746f",84,"8d05f",318,"28663",618,"82949",87,"62406",88,"29a52",89,"8b7a3",90,"f1743",91,"75207",629,"a5bd1",326,"ce63b",328,"3d942",633,"97510",93,"09403",94,"41736",95,"dbf3f",96,"459f2",331,"31927",335,"8dd9e",98,"21a6e",338,"aada2",99,"8a868",339,"e0ea7",340,"bf890",341,"24cf4",101,"c71d0",344,"8f352",346,"d6127",650,"0b50d",102,"b9a40"],"native":[104,"dc499",0,"84270",105,"3284d",106,"179cd",1,"9e95c",2,"1c615",108,"23463",3,"8aebd",4,"59c72",5,"aac34",111,"f15b4",6,"0aa6f",7,"30f63",8,"1c00c",112,"e849c",113,"f9644",9,"5672c",116,"7bf16",117,"ec4c7",10,"3c2e7",118,"d2491",119,"4a449",11,"63fec",125,"88dc5",12,"c5aaa",126,"fe6c0",127,"674e9",13,"8508c",128,"1576e",130,"d1ccc",131,"e51c4",14,"75317",133,"a80b7",135,"b278b",15,"6fd2d",16,"68c23",138,"eab1c",139,"0a54a",141,"026d6",142,"34e74",17,"c5d80",18,"8cc81",146,"cdef6",147,"da80e",19,"1832b",20,"e704b",149,"57d0b",153,"d67d3",21,"21b45",154,"9d530",22,"6fbab",155,"8752a",23,"921bf",24,"9d7ed",159,"ea2f1",25,"1dacb",26,"7f916",160,"1f173",27,"c94c5",164,"895e1",165,"80118",166,"820e2",167,"5c916",28,"ca148",29,"f32e5",169,"be527",170,"215a4",171,"2fe6a",30,"ee0f3",173,"176e2",175,"2dc25",176,"5f1d9",178,"f740b",183,"913be",184,"66754",31,"a14c0",32,"8b3e4",185,"008ad",186,"0c447",33,"b58cc",190,"ed66f",34,"4d0fa",35,"ec907",193,"3794f",194,"2a738",36,"44771",37,"3be7d",196,"f27d5",38,"45523",197,"adbe2",198,"397d7",199,"a15f9",202,"451ef",203,"6d3cf",204,"c06a9",205,"11673",39,"49305",207,"f2b58",209,"e4167",210,"237da",213,"015ca",40,"5219e",218,"1e8d4",41,"11de0",220,"646d8",221,"7fcd6",42,"0afd5",223,"eb149",226,"974e7",43,"2a31d",229,"cb10c",230,"86f5b",44,"14280",231,"af215",232,"fe52f",45,"e4bf1",46,"2036c",234,"4a2ca",237,"4981d",238,"0cd54",47,"2a623",239,"f09a4",48,"9c117",245,"f6680",246,"df5d0",49,"e7d4e",249,"231b4",50,"260df",253,"6d8b3",255,"2816b",256,"422ab",51,"49367",52,"adcc6",258,"816cf",53,"b3553",54,"e81a8",259,"bd511",55,"f8588",56,"b03c3",260,"de2fe",57,"297d5",58,"c2cab",264,"d9a9d",265,"5bd9b",59,"3cba7",60,"db3d4",61,"acaa0",269,"3aad0",62,"b713b",273,"4d275",275,"4d5d7",63,"236e8",64,"2a160",276,"83fcc",65,"ac90a",277,"9c07f",66,"1fe1b",279,"69819",280,"01172",67,"b31b3",68,"5371c",281,"56979",69,"28bb3",282,"80769",284,"0838a",286,"22ae6",289,"c53c6",70,"c5737",71,"d3226",72,"fcfa8",73,"b9cec",74,"b37b9",75,"482f1",293,"35ede",76,"202ea",77,"4a4b4",78,"59c72",299,"01dea",79,"773d1",300,"46bb6",301,"5f57e",302,"fe002",303,"f3c8e",80,"ce97c",305,"cdbc9",81,"9eeaf",82,"6d00f",307,"6aeab",308,"cbc12",83,"1814a",84,"9693c",85,"020da",86,"48676",317,"76f48",87,"d048e",88,"394e3",321,"19fb1",322,"3f786",323,"90cf4",89,"0d3fb",90,"90f73",91,"3102b",324,"68d7f",327,"bbd4b",329,"39206",92,"ef727",93,"5658a",94,"81220",95,"9c470",96,"bbe52",332,"abd66",333,"18187",334,"e1188",97,"bc6e9",98,"71ed8",99,"95e6a",100,"ca148",101,"a9913",342,"1b51d",343,"f144d",345,"0db3e",347,"933c9",102,"fd726",103,"7f916"]}}