[1,["26FSxtvVlFoJFF1XAmtnaw","acus9envFKV4r9wg+eLbiP","54Uz8M1uVBYpphuspT5g4s","0e814cMshLv6JHsBYFltjq","85FKJpkBhI4L2pbLuWwT1g","a8iwaDxbhCx7N2TZZCt+5B","6cZSMrZVRJD4JFaq8VWN6h","f179ymRtxGI4Y7/q7D53xM","6bfKakanxE9ZWzvhFCeC68","23oHEOcWNAy62YTYSqT76P","7bioLL93VI+b6kVdpILF4b","ecqQ0Eg6hMjKI9RKpVwkMM","fbfDiUV9hJragsdKa3nDkR","8di1rNqwpMSroys8NB5DV1","5dCYTbHnVKlJFrZ+AjZJPG","0ar6g6caJIhJRW1ldIqTDQ","46WgzuJBhFPqVKFpRbg5c1","daRl2bGqdAM6OIsQDd+Ldb","acwa7uydlFjaAVWhwmSp45","6770vAC05DCr7Du++VWoM9","303AIVG65CgJzTyg6ONX6f","f1wkR+M0hNj6Pnp1nNv/Jh","f4LihUm9ZME7c3XeV35mLF","af1OqO9eJHw5gIEe+ig+en","1ec/G8seNJ7460aPlo4J1H","fd5rm5BYtDYZLYNWxNGri/","1dXIKd0h5E2axyE1HpEQhb","b77/WjtBBEar8wIIGZItdq","60NqRkyQpMuZMccQHVektg","9ah4ZtZkNEu4SrO5kyLENx","e3Zu58qrFPx45dDtDpxaZO","c7FApy3PVFDoLgFUs6e2kG","c77P2xJbNB2KP04Id47wiF","b3SAtWUClMf4a7Qca70mhZ","eauA/+KgBIjrIX4TazDdyn","08moofIiNPvrnBGd6hmN21","03HRVS5HhM35x8QRqqMomK","dcXRJeCvdH8I36+sbrmvBS","74sm/yc7RFxpB3vQ4mRkdp","0a7tvpWCxDAoHrjrF3D9a2","0bdi88VKVIn7ajhYiUc9MQ","33OvEmdSxMVZDeWXQAB3mk","47vMJjQOpMcbgLXsOM5o0x","6d91qAgpRO7rTnUdo+XTgZ","b5jgGPAOhGn5vQ1uEQT+mb","4eCQgZU01DrLY3LtzE1KoY","d4JvrNcd1Jqow2pJy5Bo/I","5evNI+Le5MNpQ4+JM1918O","84BJJ9MOZOyonJHEjnh3gV","fbteUR1oFI7IRAg/CWtkOP","87IFW431JKd5DyY6UttDWe","91j6koUjJBmpoGruE0Ytn6"],["_textureSetter","rank1","rank10","rank11","rank12","rank2","rank3","rank4","rank5","rank6","rank7","rank8","rank9","s_1","s_10","s_11","s_12","s_13","s_14","s_15","s_16","s_2","s_3","s_4","s_5","s_6","s_7","s_8","s_9","w_ak","w_cfq","w_cjj","w_dao","w_dg","w_fs","w_gj","w_gtst","w_hdl","w_jgb","w_jtl","w_ju","w_ld","w_mb","w_mq","w_nnp","w_rsq","w_sd","w_sq","w_sq2","w_szg","w_tb","w_tj"],["cc.SpriteFrame",["cc.SpriteAtlas",["_name","_spriteFrames"],2,11]],[[1,0,1,2]],[[[{"name":"s_11","rect":[897,650,114,111],"offset":[0,0],"originalSize":[114,111],"rotated":1,"capInsets":[0,0,0,0]}],[0],0,[0],[0],[0]],[[{"name":"rank11","rect":[318,554,159,159],"offset":[0,0],"originalSize":[159,159],"capInsets":[0,0,0,0]}],[0],0,[0],[0],[0]],[[{"name":"s_7","rect":[505,452,120,120],"offset":[0,0],"originalSize":[120,120],"capInsets":[0,0,0,0]}],[0],0,[0],[0],[0]],[[{"name":"s_5","rect":[316,919,113,120],"offset":[0,0],"originalSize":[113,120],"capInsets":[0,0,0,0]}],[0],0,[0],[0],[0]],[[{"name":"rank6","rect":[2,869,155,159],"offset":[0,0],"originalSize":[155,159],"capInsets":[0,0,0,0]}],[0],0,[0],[0],[0]],[[{"name":"s_16","rect":[599,810,120,100],"offset":[0,0],"originalSize":[120,100],"capInsets":[0,0,0,0]}],[0],0,[0],[0],[0]],[[[0,"icon.plist",[{},"rank1",6,0,"rank10",6,1,"rank11",6,2,"rank12",6,3,"rank2",6,4,"rank3",6,5,"rank4",6,6,"rank5",6,7,"rank6",6,8,"rank7",6,9,"rank8",6,10,"rank9",6,11,"s_1",6,12,"s_10",6,13,"s_11",6,14,"s_12",6,15,"s_13",6,16,"s_14",6,17,"s_15",6,18,"s_16",6,19,"s_2",6,20,"s_3",6,21,"s_4",6,22,"s_5",6,23,"s_6",6,24,"s_7",6,25,"s_8",6,26,"s_9",6,27,"w_ak",6,28,"w_cfq",6,29,"w_cjj",6,30,"w_dao",6,31,"w_dg",6,32,"w_fs",6,33,"w_gj",6,34,"w_gtst",6,35,"w_hdl",6,36,"w_jgb",6,37,"w_jtl",6,38,"w_ju",6,39,"w_ld",6,40,"w_mb",6,41,"w_mq",6,42,"w_nnp",6,43,"w_rsq",6,44,"w_sd",6,45,"w_sq",6,46,"w_sq2",6,47,"w_szg",6,48,"w_tb",6,49,"w_tj",6,50]]],0,0,[0,0,0,0,0,0,0,0,0,0,0,0,0,0,0,0,0,0,0,0,0,0,0,0,0,0,0,0,0,0,0,0,0,0,0,0,0,0,0,0,0,0,0,0,0,0,0,0,0,0,0],[1,2,3,4,5,6,7,8,9,10,11,12,13,14,15,16,17,18,19,20,21,22,23,24,25,26,27,28,29,30,31,32,33,34,35,36,37,38,39,40,41,42,43,44,45,46,47,48,49,50,51],[1,2,3,4,5,6,7,8,9,10,11,12,13,14,15,16,17,18,19,20,21,22,23,24,25,26,27,28,29,30,31,32,33,34,35,36,37,38,39,40,41,42,43,44,45,46,47,48,49,50,51]],[[{"name":"s_12","rect":[431,919,113,120],"offset":[0,0],"originalSize":[113,120],"capInsets":[0,0,0,0]}],[0],0,[0],[0],[0]],[[{"name":"rank10","rect":[611,649,159,159],"offset":[0,0],"originalSize":[159,159],"capInsets":[0,0,0,0]}],[0],0,[0],[0],[0]],[[{"name":"s_10","rect":[893,883,112,113],"offset":[0,0],"originalSize":[112,113],"rotated":1,"capInsets":[0,0,0,0]}],[0],0,[0],[0],[0]],[[{"name":"s_9","rect":[895,766,113,115],"offset":[0,0],"originalSize":[113,115],"capInsets":[0,0,0,0]}],[0],0,[0],[0],[0]],[[{"name":"s_15","rect":[163,776,91,99],"offset":[0,0],"originalSize":[91,99],"rotated":1,"capInsets":[0,0,0,0]}],[0],0,[0],[0],[0]],[[{"name":"rank5","rect":[159,869,155,159],"offset":[0,0],"originalSize":[155,159],"capInsets":[0,0,0,0]}],[0],0,[0],[0],[0]],[[{"name":"rank3","rect":[166,493,159,150],"offset":[0,0],"originalSize":[159,150],"rotated":1,"capInsets":[0,0,0,0]}],[0],0,[0],[0],[0]],[[{"name":"rank7","rect":[627,488,159,170],"offset":[0,0],"originalSize":[159,170],"rotated":1,"capInsets":[0,0,0,0]}],[0],0,[0],[0],[0]],[[{"name":"rank12","rect":[320,385,183,167],"offset":[0,0],"originalSize":[183,167],"capInsets":[0,0,0,0]}],[0],0,[0],[0],[0]],[[{"name":"s_1","rect":[775,873,112,116],"offset":[0,0],"originalSize":[112,116],"rotated":1,"capInsets":[0,0,0,0]}],[0],0,[0],[0],[0]],[[{"name":"rank2","rect":[855,206,159,153],"offset":[0,0],"originalSize":[159,153],"rotated":1,"capInsets":[0,0,0,0]}],[0],0,[0],[0],[0]],[[{"name":"rank1","rect":[2,708,159,159],"offset":[0,0],"originalSize":[159,159],"capInsets":[0,0,0,0]}],[0],0,[0],[0],[0]],[[{"name":"s_14","rect":[775,762,118,109],"offset":[0,0],"originalSize":[118,109],"capInsets":[0,0,0,0]}],[0],0,[0],[0],[0]],[[{"name":"s_4","rect":[479,681,120,120],"offset":[0,0],"originalSize":[120,120],"capInsets":[0,0,0,0]}],[0],0,[0],[0],[0]],[[{"name":"w_dg","rect":[547,330,120,86],"offset":[0,0],"originalSize":[120,86],"rotated":1,"capInsets":[0,0,0,0]}],[0],0,[0],[0],[0]],[[{"name":"s_8","rect":[477,803,120,114],"offset":[0,0],"originalSize":[120,114],"capInsets":[0,0,0,0]}],[0],0,[0],[0],[0]],[[{"name":"s_13","rect":[163,654,120,120],"offset":[0,0],"originalSize":[120,120],"capInsets":[0,0,0,0]}],[0],0,[0],[0],[0]],[[{"name":"rank8","rect":[799,489,159,164],"offset":[0,0],"originalSize":[159,164],"rotated":1,"capInsets":[0,0,0,0]}],[0],0,[0],[0],[0]],[[{"name":"s_2","rect":[546,919,120,113],"offset":[0,0],"originalSize":[120,113],"rotated":1,"capInsets":[0,0,0,0]}],[0],0,[0],[0],[0]],[[{"name":"rank4","rect":[316,715,155,159],"offset":[0,0],"originalSize":[155,159],"rotated":1,"capInsets":[0,0,0,0]}],[0],0,[0],[0],[0]],[[{"name":"s_3","rect":[661,912,120,112],"offset":[0,0],"originalSize":[120,112],"rotated":1,"capInsets":[0,0,0,0]}],[0],0,[0],[0],[0]],[[{"name":"rank9","rect":[2,547,159,159],"offset":[0,0],"originalSize":[159,159],"capInsets":[0,0,0,0]}],[0],0,[0],[0],[0]],[[{"name":"s_6","rect":[775,650,120,110],"offset":[0,0],"originalSize":[120,110],"capInsets":[0,0,0,0]}],[0],0,[0],[0],[0]]]]